senate_hearings/__init__.py
senate_hearings/helper_funcs.py
senate_hearings/keybert_funcs.py
senate_hearings-0.1.1.dist-info/licenses/LICENSE
senate_hearings-0.1.1.dist-info/METADATA
senate_hearings-0.1.1.dist-info/WHEEL
senate_hearings-0.1.1.dist-info/top_level.txt
senate_hearings-0.1.1.dist-info/RECORD
